{"name":"participant","participant":["RuoteAMQP::Participant",{"queue":"rpm.work_items.dev"}],"_rev":2,"original_tree":["participant",{"task_type":"yes_no","due_in":"30 business days","task":"verify_payment_received","response_field":"payment_received_in_30_days","question":"Has there any payment been received within the last 30 days? ","ref":"entry"},[]],"variables":null,"on_timeout":null,"put_at":"2010-11-18 00:50:03.333512 UTC","participant_name":"entry","dispatched":true,"_id":"0_4_2_0!!20101118-giyatare","applied_workitem":{"participant_name":"entry","fields":{"context_id":"4ce4709ace47d00c91000013","current_balance":1470.48,"payer":{"name":"Health Plan of San Mateo - MEDICARE","payer_type":"Medicare","payer_id":"4cddd9c0464199221600111f"},"context_type":"InsuranceClaim","total_payments":0.0,"total_write_offs":24.25,"follow_up_count":0,"primary_payer":{"name":"Health Plan of San Mateo - MEDICARE","payer_type":"Medicare","payer_id":"4cddd9c0464199221600111f"},"total_charges":1494.73,"patient_id":"4cdddfa346419922160087f5","company_id":"4cddd999464199221600083b","patient_name":"Doe83, John","date_of_service":"2010-06-17T07:00:00Z","current_payer":{"name":"Health Plan of San Mateo - MEDICARE","payer_type":"Medicare","payer_id":"4cddd9c0464199221600111f"},"debug":"false","params":{"task_type":"yes_no","task":"verify_payment_received","due_in":"30 business days","ref":"entry","question":"Has there any payment been received within the last 30 days? ","response_field":"payment_received_in_30_days"},"transport_unit_name":"","balance_threshold":100},"fei":{"sub_wfid":null,"wfid":"20101118-giyatare","engine_id":"engine","expid":"0_4_2_0"}},"type":"expressions","created_time":"2010-11-18 00:50:03.325110 UTC","on_cancel":null,"parent_id":{"sub_wfid":null,"wfid":"20101118-giyatare","engine_id":"engine","expid":"0_4_2"},"forgotten":null,"children":[],"tagname":null,"fei":{"sub_wfid":null,"wfid":"20101118-giyatare","engine_id":"engine","expid":"0_4_2_0"},"on_error":null}